{
  "responses": {
    "Which of these is the best example of a strong password?": "g6$L7@QwZ9p#",
    "Why should you not use the same password for all your accounts?": "If one leaks, all your accounts can be hacked",
    "What does a password saving app do?": "Writes them on paper",
    "Why is it risky to use personal info like your birthday in a password?": "It makes the password shorter",
    "Why is it important to keep your password private even from close friends?": "Friends will remember it better than you",
    "Why is Two-Factor Authentication (2FA) important?": "It works only on phones",
    "What should you do if a site says your password was leaked in a breach?": "Change it only if you remember",
    "How often should you change important passwords (like email or banking)?": "Every 6 months or after suspicious activity",
    "What is a safe way to share a password (if you must)?": "Post it in a private Facebook group",
    "Which of these actions increases your password security the most?": "Reusing passwords on trusted websites"
  },
  "scores": {
    "Which of these is the best example of a strong password?": {
      "answer": "g6$L7@QwZ9p#",
      "score": 10,
      "level": "Advanced"
    },
    "Why should you not use the same password for all your accounts?": {
      "answer": "If one leaks, all your accounts can be hacked",
      "score": 10,
      "level": "Advanced"
    },
    "What does a password saving app do?": {
      "answer": "Writes them on paper",
      "score": 3,
      "level": "Beginner"
    },
    "Why is it risky to use personal info like your birthday in a password?": {
      "answer": "It makes the password shorter",
      "score": 0,
      "level": "Wrong"
    },
    "Why is it important to keep your password private even from close friends?": {
      "answer": "Friends will remember it better than you",
      "score": 0,
      "level": "Wrong"
    },
    "Why is Two-Factor Authentication (2FA) important?": {
      "answer": "It works only on phones",
      "score": 3,
      "level": "Beginner"
    },
    "What should you do if a site says your password was leaked in a breach?": {
      "answer": "Change it only if you remember",
      "score": 3,
      "level": "Beginner"
    },
    "How often should you change important passwords (like email or banking)?": {
      "answer": "Every 6 months or after suspicious activity",
      "score": 10,
      "level": "Advanced"
    },
    "What is a safe way to share a password (if you must)?": {
      "answer": "Post it in a private Facebook group",
      "score": 0,
      "level": "Wrong"
    },
    "Which of these actions increases your password security the most?": {
      "answer": "Reusing passwords on trusted websites",
      "score": 0,
      "level": "Wrong"
    }
  },
  "total_score": 39,
  "percentage": 39.0,
  "overall_level": "Basic"
}